{"IcoMoonType":"selection","icons":[{"icon":{"paths":["M1016.988 652.010l-256-320c-6.074-7.592-15.266-12.010-24.988-12.010h-448c-9.72 0-18.916 4.418-24.988 12.010l-256 320c-4.538 5.674-7.012 12.724-7.012 19.99v288c0 35.346 28.654 64 64 64h896c35.348 0 64-28.654 64-64v-288c0-7.266-2.472-14.316-7.012-19.99zM960 704h-224l-128 128h-192l-128-128h-224v-20.776l239.38-299.224h417.24l239.38 299.224v20.776z","M736 512h-448c-17.672 0-32-14.328-32-32s14.328-32 32-32h448c17.674 0 32 14.328 32 32s-14.326 32-32 32z","M800 640h-576c-17.672 0-32-14.326-32-32s14.328-32 32-32h576c17.674 0 32 14.326 32 32s-14.326 32-32 32z"],"tags":["drawer","box","inbox","archive","category"],"defaultCode":59740,"grid":16,"attrs":[]},"attrs":[],"properties":{"ligatures":"drawer, box","name":"drawer","order":2,"id":93,"prevSize":32,"code":59740},"setIdx":0,"setId":1,"iconIdx":92}],"height":1024,"metadata":{"name":"icomoon"},"preferences":{"showGlyphs":true,"showQuickUse":true,"showQuickUse2":true,"showSVGs":true,"fontPref":{"prefix":"icon-","metadata":{"fontFamily":"icomoon"},"metrics":{"emSize":1024,"baseline":6.25,"whitespace":50},"embed":false},"imagePref":{"prefix":"icon-","png":true,"useClassSelector":true,"color":0,"bgColor":16777215,"classSelector":".icon"},"historySize":50,"showCodes":true,"gridSize":16}}